nonebot_plugin_cnrail-0.3.0.dist-info/METADATA
nonebot_plugin_cnrail-0.3.0.dist-info/WHEEL
nonebot_plugin_cnrail-0.3.0.dist-info/entry_points.txt
nonebot_plugin_cnrail-0.3.0.dist-info/licenses/LICENSE
nonebot_plugin_cnrail/__init__.py
nonebot_plugin_cnrail/__main__.py
nonebot_plugin_cnrail/config.py
nonebot_plugin_cnrail/data_source.py
nonebot_plugin_cnrail/debug.py
nonebot_plugin_cnrail/models.py
nonebot_plugin_cnrail/render.py
nonebot_plugin_cnrail/res/assets/index.css
nonebot_plugin_cnrail/res/assets/index.mjs
nonebot_plugin_cnrail/res/templates/train_table.html.jinja
nonebot_plugin_cnrail/utils.py
nonebot_plugin_cnrail-0.3.0.dist-info/RECORD
