Metadata-Version: 2.1
Name: nonebot-plugin-cnrail
Version: 0.3.0
Summary: NoneBot2 plugin for query the train time table
Home-page: https://github.com/lgc-NB2Dev/nonebot-plugin-cnrail
Author-Email: student_2333 <lgc2333@126.com>, XieXiLin <support@xiexilin.com>
License: MIT
Project-URL: Homepage, https://github.com/lgc-NB2Dev/nonebot-plugin-cnrail
Requires-Python: <4.0,>=3.9
Requires-Dist: nonebot2>=2.3.1
Requires-Dist: httpx>=0.27.0
Requires-Dist: nonebot-plugin-alconna>=0.48.0
Requires-Dist: nonebot-plugin-htmlrender>=0.3.2
Requires-Dist: jinja2>=3.1.4
Requires-Dist: pytz>=2024.1
Requires-Dist: cookit[jinja,loguru,playwright,pyd]>=0.8.1
